pyurl/__init__.py
pyurl/pyurl.py
tests/__init__.py
tests/test_pyurl.py
pyurl-0.1.2.dist-info/LICENSE
pyurl-0.1.2.dist-info/METADATA
pyurl-0.1.2.dist-info/WHEEL
pyurl-0.1.2.dist-info/entry_points.txt
pyurl-0.1.2.dist-info/top_level.txt
pyurl-0.1.2.dist-info/RECORD
