Metadata-Version: 2.1
Name: pyurl
Version: 0.1.2
Summary: Website new updates/blogs CLI notifier
Home-page: https://github.com/ydcjeff/pyurl
Author: Jeff Yang
Author-email: ydc.jeff@gmail.com
License: UNKNOWN
Project-URL: Bug Reports, https://github.com/ydcjeff/pyurl/issues
Project-URL: Source, https://github.com/ydcjeff/pyurl/
Keywords: url,web scrapper,cli
Platform: UNKNOWN
Classifier: Development Status :: 5 - Production/Stable
Classifier: Intended Audience :: Developers
Classifier: Environment :: Console
Classifier: Topic :: Utilities
Classifier: License :: OSI Approved :: MIT License
Classifier: Programming Language :: Python :: 3.5
Classifier: Programming Language :: Python :: 3.6
Classifier: Programming Language :: Python :: 3.7
Classifier: Programming Language :: Python :: 3.8
Classifier: Programming Language :: Python :: 3 :: Only
Requires-Python: >=3.6.0, <4
Requires-Dist: requests
Requires-Dist: beautifulsoup4
Requires-Dist: lxml
Provides-Extra: test
Requires-Dist: pytest ; extra == 'test'
Requires-Dist: flake8 ; extra == 'test'
Requires-Dist: black ; extra == 'test'
Requires-Dist: isort ; extra == 'test'
Requires-Dist: pytest-cov ; extra == 'test'
Requires-Dist: codecov ; extra == 'test'
